{
  "CurrencyRates": [
    {
      "FromCurrency": "EUR",
      "ToCurrency": "USD",
      "Rate": 1.144337
    },
    {
      "FromCurrency": "USD",
      "ToCurrency": "JPY",
      "Rate": 110.415
    },
    {
      "FromCurrency": "GBP",
      "ToCurrency": "USD",
      "Rate": 1.26673
    },
    {
      "FromCurrency": "USD",
      "ToCurrency": "CHF",
      "Rate": 0.98097
    },
    {
      "FromCurrency": "USD",
      "ToCurrency": "CAD",
      "Rate": 1.36435
    },
    {
      "FromCurrency": "EUR",
      "ToCurrency": "JPY",
      "Rate": 126.357
    },
    {
      "FromCurrency": "AUD",
      "ToCurrency": "USD",
      "Rate": 0.7054
    },
    {
      "FromCurrency": "EUR",
      "ToCurrency": "CHF",
      "Rate": 1.12275
    },
    {
      "FromCurrency": "EUR",
      "ToCurrency": "CAD",
      "Rate": 1.54294
    },
    {
      "FromCurrency": "GBP",
      "ToCurrency": "JPY",
      "Rate": 137.59
    },
    {
      "FromCurrency": "GBP",
      "ToCurrency": "CHF",
      "Rate": 1.24503
    },
    {
      "FromCurrency": "GBP",
      "ToCurrency": "CAD",
      "Rate": 1.71065
    },
    {
      "FromCurrency": "AUD",
      "ToCurrency": "JPY",
      "Rate": 76.5386
    },
    {
      "FromCurrency": "AUD",
      "ToCurrency": "CHF",
      "Rate": 0.692571
    },
    {
      "FromCurrency": "AUD",
      "ToCurrency": "CAD",
      "Rate": 0.692568
    }
  ]
}
